{"cameraMode":{"drawMode":0,"name":"Shaded","section":"Shading Mode"},"sceneLighting":true,"audioPlay":false,"sceneViewState":{"m_AlwaysRefresh":false,"showFog":true,"showSkybox":true,"showFlares":true,"showImageEffects":true,"showParticleSystems":true,"showVisualEffectGraphs":true,"m_FxEnabled":true},"in2DMode":false,"pivot":{"x":-2.7014057636260988,"y":1.8123862743377686,"z":-10.54210376739502},"rotation":{"x":-0.07203636318445206,"y":-0.39320895075798037,"z":-0.04056868329644203,"w":0.9169666767120361},"size":0.17448900640010835,"orthographic":false}